[
  {
    "utilisateur": "Ngn.Boris",
    "appareils": "Samsung Galaxie S8",
    "connexion": "Samedi 24 Février 2024",
    "status": "Connecté"
  },
  
  {
    "utilisateur": "Ngn.Boris",
    "appareils": "Samsung Galaxie S8",
    "connexion": "Samedi 24 Février 2024",
    "status": "Connecté"
  },
  {
    "utilisateur": "Ngn.Boris",
    "appareils": "Samsung Galaxie S8",
    "connexion": "Samedi 24 Février 2024",
    "status": "Connecté"
  },
  
  {
    "utilisateur": "Ngn.Boris",
    "appareils": "Samsung Galaxie S8",
    "connexion": "Samedi 24 Février 2024",
    "status": "Connecté"
  },
  {
    "utilisateur": "Ngn.Boris",
    "appareils": "Samsung Galaxie S8",
    "connexion": "Samedi 24 Février 2024",
    "status": "Connecté"
  },
  
  {
    "utilisateur": "Ngn.Boris",
    "appareils": "Samsung Galaxie S8",
    "connexion": "Samedi 24 Février 2024",
    "status": "Connecté"
  }
]
